lines/__init__.py
lines/lines.py
lines/lines_gui.py
lines/peakdetect.py
xpdlines-2.0.1.dist-info/LICENCE
xpdlines-2.0.1.dist-info/METADATA
xpdlines-2.0.1.dist-info/WHEEL
xpdlines-2.0.1.dist-info/entry_points.txt
xpdlines-2.0.1.dist-info/top_level.txt
xpdlines-2.0.1.dist-info/RECORD
