Metadata-Version: 2.1
Name: xpdlines
Version: 2.0.1
Summary: A program for plotting powder diffraction patterns and background subtraction
Home-page: https://github.com/stefsmeets/lines
Author: Stef Smeets
Author-email: s.smeets@esciencecenter.nl
Project-URL: Bug Tracker, https://github.com/stefsmeets/lines/issues
Project-URL: Documentation, https://github.com/stefsmeets/lines
Keywords: plotting,powder-diffraction,background-correction,profile-refinement
Classifier: Development Status :: 5 - Production/Stable
Classifier: Intended Audience :: Developers
Classifier: Intended Audience :: Science/Research
Classifier: License :: OSI Approved :: MIT License
Classifier: Natural Language :: English
Classifier: Programming Language :: Python :: 3
Classifier: Programming Language :: Python :: 3.9
Classifier: Programming Language :: Python :: 3.10
Classifier: Programming Language :: Python :: 3.11
Classifier: Topic :: Scientific/Engineering
License-File: LICENCE
Requires-Dist: matplotlib
Requires-Dist: numpy
Requires-Dist: scipy
Provides-Extra: build
Requires-Dist: twine ; extra == 'build'
Requires-Dist: wheel ; extra == 'build'
Requires-Dist: build ; extra == 'build'
